xs/setup.py
xs/xs.py
llm_xs-1.0.0.dist-info/LICENSE
llm_xs-1.0.0.dist-info/METADATA
llm_xs-1.0.0.dist-info/WHEEL
llm_xs-1.0.0.dist-info/top_level.txt
llm_xs-1.0.0.dist-info/RECORD
