Metadata-Version: 2.1
Name: llm-xs
Version: 1.0.0
Summary: A module for creation of endpoint for the open-sourced LLMs
Author-email: Prabhudayal Vaishnav <pradachan@tuta.io>
License: MIT
License-File: LICENSE
Requires-Dist: flask
Requires-Dist: pyngrok
Requires-Dist: waitress
